auth_control/__init__.py
auth_control/core.cp38-win_amd64.pyd
auth_control/core.cpp
auth_control/core.pyx
auth_control/core_py.py
auth_control/license_validator.py
auth_control/models.py
auth_control/permission.py
auth_control/policies.py
auth_control_sdk-1.0.1.dist-info/METADATA
auth_control_sdk-1.0.1.dist-info/WHEEL
auth_control_sdk-1.0.1.dist-info/top_level.txt
auth_control_sdk-1.0.1.dist-info/RECORD
